[
    {
        "name":"event_StartGame",
        "text":"event_StartGame_desc",
        "choices":[
            {
                "text":"event_StartGame_choice1_desc"
            }
        ]
    },
    {
        "name":"篡改宇宙法则-圆周率",
        "text":"篡改宇宙法则-圆周率\n\n我们在对现实进行精确而广泛的编辑方面取得了巨大的成功。我们把圆周率这个数学常数给取整了，这样计算起来可就容易多了。当然，由此产生的变化推翻了一些数学和科学模型，但这只是暂时的；一切很快就会恢复正常。",
        "choices":[
            {
                "text":"圆周率被取整了！？"
            },
            {
                "text":"至少更好算了。"
            }
        ]
    },
    {
        "name":"篡改宇宙法则-真空光速",
        "text":"篡改宇宙法则-真空光速\n\n我们对现实的一个实验让光速显著变快了！这导致恒星能量输出的提升确实不错，但我们也担心会对殖民地造成长期影响。一切终会逐渐恢复正常，但在那之前或许还要做最坏的准备。",
        "choices":[
            {
                "text":"这是怎么发生的？"
            },
            {
                "text":"太好玩了！"
            },
            {
                "text":"这能有什么坏处？"
            }
        ]
    },
]